{
  "housePlans": [
    {
      "id": "plan-1763013670372",
      "title": "testing 2",
      "description": "",
      "plotDimension": "30x40",
      "bhk": "2",
      "floors": 2,
      "facing": "north",
      "price": 15677,
      "image": "/uploads/house-plans/image-1763013670370-804608581.png",
      "features": [],
      "area": 1500,
      "style": "modern",
      "isAvailable": true,
      "uploadedBy": "admin",
      "createdAt": "2025-11-13T06:01:10.372Z",
      "updatedAt": "2025-11-13T06:01:10.372Z"
    }
  ]
}